full_text_search/__init__.py
full_text_search/common.py
full_text_search/chat/parse_reply.py
full_text_search/index/__init__.py
full_text_search/index/sqlite_index.py
full_text_search/index/tantivy_index.py
full_text_search/ingest/common.py
full_text_search/ingest/enrich.py
full_text_search/ingest/ingest_docx.py
full_text_search/ingest/ingest_html.py
full_text_search/ingest/ingest_html_ast.py
full_text_search/ingest/ingest_markdown.py
full_text_search/ingest/ingest_pdf.py
full_text_search/ingest/split.py
full_text_search/mcp/deep_research_mcp.py
full_text_search/mcp/mcp.py
full_text_search/mcp/multi_deep_research_mcp.py
full_text_search/mcp/multi_mcp.py
full_text_search/mcp/unified_deep_research_mcp.py
full_text_search/server/__init__.py
full_text_search/server/api.py
fts_mcp-0.0.8.dist-info/METADATA
fts_mcp-0.0.8.dist-info/WHEEL
fts_mcp-0.0.8.dist-info/entry_points.txt
fts_mcp-0.0.8.dist-info/top_level.txt
fts_mcp-0.0.8.dist-info/RECORD
