Metadata-Version: 2.4
Name: fts-mcp
Version: 0.0.8
Summary: Add your description here
Requires-Python: >=3.11
Requires-Dist: html-to-markdown
Requires-Dist: markdownify
Requires-Dist: lenlp
Requires-Dist: tantivy
Requires-Dist: rapidfuzz
Requires-Dist: fastmcp>=2.12.5
Requires-Dist: lm_deluge>=0.0.68
Requires-Dist: modal
Requires-Dist: pandas
Requires-Dist: pypdf
Requires-Dist: rich
Requires-Dist: pyyaml
Requires-Dist: fastapi
Requires-Dist: uvicorn
